{
  "en": {
    "title": "Therapeutic Movies",
    "description": "Movies that explore mental health themes and can provide therapeutic value.",
    "items": [
      {
        "id": "movie-1",
        "title": "Inside Out",
        "description": "A beautifully animated exploration of emotions and how they shape our experiences and memories. The film follows Riley, a young girl whose emotions - Joy, Sadness, Anger, Fear, and Disgust - guide her through a difficult transition in her life. This movie provides valuable insights into emotional intelligence and mental health.",
        "director": "Pete Docter, Ronnie Del Carmen",
        "year": 2015,
        "duration": "95 minutes",
        "rating": "PG",
        "streamingUrl": "https://www.disneyplus.com/movies/inside-out",
        "trailerUrl": "https://www.youtube.com/watch?v=yRUAzGQ3nSY",
        "image": "https://example.com/movie1.jpg",
        "themes": [
          "emotional intelligence",
          "mental health",
          "psychology",
          "emotions",
          "growing up"
        ],
        "benefits": [
          "emotional understanding",
          "mental health awareness",
          "emotional processing",
          "family communication"
        ]
      },
      {
        "id": "movie-2",
        "title": "Good Will Hunting",
        "description": "A powerful drama about a young man with extraordinary mathematical abilities who struggles with emotional trauma and trust issues. Through therapy sessions with a compassionate psychologist, he learns to confront his past and open himself to meaningful relationships. The film beautifully portrays the therapeutic process and healing.",
        "director": "Gus Van Sant",
        "year": 1997,
        "duration": "126 minutes",
        "rating": "R",
        "streamingUrl": "https://www.netflix.com/title/good-will-hunting",
        "trailerUrl": "https://www.youtube.com/watch?v=PaZVjZEFkRs",
        "image": "https://example.com/movie2.jpg",
        "themes": [
          "therapy",
          "trauma healing",
          "psychology",
          "emotional growth",
          "trust"
        ],
        "benefits": [
          "therapy understanding",
          "trauma processing",
          "emotional healing",
          "relationship building"
        ]
      },
      {
        "id": "movie-3",
        "title": "A Beautiful Mind",
        "description": "The biographical drama tells the story of John Nash, a brilliant mathematician who struggles with schizophrenia. The film provides insight into mental illness, the importance of support systems, and the possibility of living a fulfilling life despite mental health challenges. It reduces stigma and promotes understanding.",
        "director": "Ron Howard",
        "year": 2001,
        "duration": "135 minutes",
        "rating": "PG-13",
        "streamingUrl": "https://www.amazon.com/beautiful-mind",
        "trailerUrl": "https://www.youtube.com/watch?v=YjmkXvGaQQs",
        "image": "https://example.com/movie3.jpg",
        "themes": [
          "mental illness",
          "schizophrenia",
          "support systems",
          "resilience",
          "stigma reduction"
        ],
        "benefits": [
          "mental health awareness",
          "stigma reduction",
          "hope and resilience",
          "support understanding"
        ]
      },
      {
        "id": "movie-4",
        "title": "The Pursuit of Happyness",
        "description": "An inspiring true story about a father and son facing homelessness while pursuing a better life. The film explores themes of perseverance, hope, and resilience in the face of overwhelming challenges. It demonstrates the importance of mental strength and determination in overcoming adversity.",
        "director": "Gabriele Muccino",
        "year": 2006,
        "duration": "117 minutes",
        "rating": "PG-13",
        "streamingUrl": "https://www.netflix.com/title/pursuit-happyness",
        "trailerUrl": "https://www.youtube.com/watch?v=89Kq8SDyvfg",
        "image": "https://example.com/movie4.jpg",
        "themes": [
          "resilience",
          "perseverance",
          "hope",
          "mental strength",
          "overcoming adversity"
        ],
        "benefits": [
          "inspiration",
          "resilience building",
          "hope cultivation",
          "mental strength"
        ]
      },
      {
        "id": "movie-5",
        "title": "Silver Linings Playbook",
        "description": "A romantic comedy-drama that sensitively portrays bipolar disorder and depression. The story follows two people with mental health challenges who find healing and hope through their relationship. The film promotes understanding of mental illness while showing that people with mental health conditions can lead fulfilling lives.",
        "director": "David O. Russell",
        "year": 2012,
        "duration": "122 minutes",
        "rating": "R",
        "streamingUrl": "https://www.hulu.com/movie/silver-linings-playbook",
        "trailerUrl": "https://www.youtube.com/watch?v=Lj5_FhLaaQQ",
        "image": "https://example.com/movie5.jpg",
        "themes": [
          "bipolar disorder",
          "depression",
          "mental health",
          "healing",
          "relationships"
        ],
        "benefits": [
          "mental health understanding",
          "stigma reduction",
          "hope and healing",
          "relationship insights"
        ]
      }
    ]
  }
}